pathvalidate_cli/__init__.py
pathvalidate_cli/__version__.py
pathvalidate_cli/_const.py
pathvalidate_cli/_logger.py
pathvalidate_cli/main.py
pathvalidate_cli-0.2.1.dist-info/licenses/LICENSE
pathvalidate_cli-0.2.1.dist-info/METADATA
pathvalidate_cli-0.2.1.dist-info/WHEEL
pathvalidate_cli-0.2.1.dist-info/entry_points.txt
pathvalidate_cli-0.2.1.dist-info/top_level.txt
pathvalidate_cli-0.2.1.dist-info/RECORD
