Metadata-Version: 2.4
Name: pathvalidate-cli
Version: 0.2.1
Summary: pathvalidate-cli is a command line interface for pathvalidate library.
Home-page: https://github.com/thombashi/pathvalidate-cli
Author: Tsuyoshi Hombashi
Author-email: tsuyoshi.hombashi@gmail.com
License: MIT License
Project-URL: Changelog, https://github.com/thombashi/pathvalidate-cli/releases
Project-URL: Source, https://github.com/thombashi/pathvalidate-cli
Project-URL: Tracker, https://github.com/thombashi/pathvalidate-cli/issues
Keywords: file,path,validate,sanitize
Classifier: Development Status :: 4 - Beta
Classifier: Environment :: Console
Classifier: Intended Audience :: Information Technology
Classifier: License :: OSI Approved :: MIT License
Classifier: Operating System :: OS Independent
Classifier: Programming Language :: Python :: 3
Classifier: Programming Language :: Python :: 3.9
Classifier: Programming Language :: Python :: 3.10
Classifier: Programming Language :: Python :: 3.11
Classifier: Programming Language :: Python :: 3.12
Classifier: Programming Language :: Python :: 3.13
Classifier: Programming Language :: Python :: 3 :: Only
Classifier: Topic :: Terminals
Classifier: Topic :: Utilities
Requires-Python: >=3.9
License-File: LICENSE
Requires-Dist: click<9,>=6.2
Requires-Dist: loguru<1,>=0.4.1
Requires-Dist: msgfy<1,>=0.2
Requires-Dist: pytablewriter<2,>=1.2
Requires-Dist: pathvalidate<4,>=3.3.0
Provides-Extra: test
Requires-Dist: pytest>=7; extra == "test"
Requires-Dist: pytest-md-report>=0.6.2; extra == "test"
Dynamic: author
Dynamic: author-email
Dynamic: classifier
Dynamic: description
Dynamic: description-content-type
Dynamic: home-page
Dynamic: keywords
Dynamic: license
Dynamic: license-file
Dynamic: project-url
Dynamic: provides-extra
Dynamic: requires-dist
Dynamic: requires-python
Dynamic: summary
